CHANGES.md
LICENSE.txt
MANIFEST.in
README.rst
setup.py
gpsdio_nmea_driver/__init__.py
gpsdio_nmea_driver/core.py
gpsdio_nmea_driver.egg-info/PKG-INFO
gpsdio_nmea_driver.egg-info/SOURCES.txt
gpsdio_nmea_driver.egg-info/dependency_links.txt
gpsdio_nmea_driver.egg-info/entry_points.txt
gpsdio_nmea_driver.egg-info/requires.txt
gpsdio_nmea_driver.egg-info/top_level.txt