Metadata-Version: 1.0
Name: gpsdio-nmea-driver
Version: 0.1
Summary: A gpsdio driver for parsing NMEA sentences directly into GPSd messages.
Home-page: https://github.com/SkyTruth/gpsdio-nmea-driver
Author: Kevin Wurster
Author-email: kevin@skytruth.org
License: Apache 2.0
Keywords: gpsdio NMEA driver AIS libais
Platform: UNKNOWN
